sagemaker_mlflow_skinny/__init__.py
sagemaker_mlflow_skinny/auth.py
sagemaker_mlflow_skinny/auth_provider.py
sagemaker_mlflow_skinny/exceptions.py
sagemaker_mlflow_skinny/mlflow_sagemaker_helpers.py
sagemaker_mlflow_skinny/mlflow_sagemaker_registry_store.py
sagemaker_mlflow_skinny/mlflow_sagemaker_request_header_provider.py
sagemaker_mlflow_skinny/mlflow_sagemaker_store.py
sagemaker_mlflow_skinny/presigned_url.py
sagemaker_mlflow_skinny-0.1.1.dist-info/LICENSE
sagemaker_mlflow_skinny-0.1.1.dist-info/METADATA
sagemaker_mlflow_skinny-0.1.1.dist-info/NOTICE
sagemaker_mlflow_skinny-0.1.1.dist-info/WHEEL
sagemaker_mlflow_skinny-0.1.1.dist-info/entry_points.txt
sagemaker_mlflow_skinny-0.1.1.dist-info/top_level.txt
sagemaker_mlflow_skinny-0.1.1.dist-info/RECORD
