Metadata-Version: 2.1
Name: sagemaker-mlflow-skinny
Version: 0.1.1
Summary: Skinny Version of AWS Plugin for MLflow with SageMaker
Home-page: https://github.com/aws/sagemaker-mlflow
Author: Amazon Web Services
License: Apache License 2.0
Classifier: Development Status :: 5 - Production/Stable
Classifier: Intended Audience :: Developers
Classifier: Natural Language :: English
Classifier: License :: OSI Approved :: Apache Software License
Classifier: Programming Language :: Python
Classifier: Programming Language :: Python :: 3.8
Classifier: Programming Language :: Python :: 3.9
Classifier: Programming Language :: Python :: 3.10
Classifier: Programming Language :: Python :: 3.11
Requires-Python: >= 3.8
License-File: LICENSE
License-File: NOTICE
Requires-Dist: boto3>=1.34
Requires-Dist: mlflow-skinny==2.13.2
Requires-Dist: pandas
Provides-Extra: test
Requires-Dist: boto3; extra == "test"
Requires-Dist: coverage<6.2,>=5.2; extra == "test"
Requires-Dist: mlflow-skinny==2.13.2; extra == "test"
Requires-Dist: pytest; extra == "test"
Requires-Dist: pytest-cov; extra == "test"
Requires-Dist: pytest-rerunfailures; extra == "test"
Requires-Dist: pytest-timeout; extra == "test"
Requires-Dist: pytest-xdist; extra == "test"
Requires-Dist: scikit-learn; extra == "test"
Provides-Extra: test-prerelease
Requires-Dist: mlflow-skinny==2.13.2; extra == "test-prerelease"
Requires-Dist: packaging; extra == "test-prerelease"
Requires-Dist: pytest; extra == "test-prerelease"
